febbox/__init__.py
febbox/febbox.py
febbox-1.0.1.dist-info/LICENSE
febbox-1.0.1.dist-info/METADATA
febbox-1.0.1.dist-info/WHEEL
febbox-1.0.1.dist-info/entry_points.txt
febbox-1.0.1.dist-info/top_level.txt
febbox-1.0.1.dist-info/RECORD
