Metadata-Version: 2.1
Name: febbox
Version: 1.0.1
Summary: CLI tool to upload files and directories to FebBox with resume capability and parallel uploads
Author-email: Jaskirat Singh Maskeen <jsmaskeen@gmail.com>
License: MIT
Keywords: febbox,uploader,cli,file-upload
Classifier: Programming Language :: Python :: 3
Classifier: Programming Language :: Python :: 3 :: Only
Classifier: Operating System :: OS Independent
Classifier: Topic :: Utilities
Classifier: License :: OSI Approved :: MIT License
Requires-Python: >=3.8
License-File: LICENSE
Requires-Dist: rich
Requires-Dist: aiohttp
